fw_gear_form_and_annotations_exporter/__init__.py
fw_gear_form_and_annotations_exporter/collect_form_annot_data.py
fw_gear_form_and_annotations_exporter/constants.py
fw_gear_form_and_annotations_exporter/flywheel_api_helpers.py
fw_gear_form_and_annotations_exporter/main.py
fw_gear_form_and_annotations_exporter/parser.py
fw_gear_form_and_annotations_exporter-0.2.5.dist-info/METADATA
fw_gear_form_and_annotations_exporter-0.2.5.dist-info/WHEEL
fw_gear_form_and_annotations_exporter-0.2.5.dist-info/licenses/LICENSE
fw_gear_form_and_annotations_exporter-0.2.5.dist-info/RECORD
