Metadata-Version: 2.4
Name: fw-gear-form-and-annotations-exporter
Version: 0.2.5
Summary: Export Form Responses and/or Annotations to CSV file(s).
Project-URL: Repository, https://gitlab.com/flywheel-io/scientific-solutions/gears/fw-gear-form-and-annotations-exporter
Author-email: Flywheel <support@flywheel.io>
License-Expression: MIT
License-File: LICENSE
Keywords: Flywheel,Gears
Classifier: Topic :: Scientific/Engineering
Requires-Python: ~=3.12
Requires-Dist: flywheel-sdk<21,>=20.1.4
Requires-Dist: fw-client<3,>=2.1.1
Requires-Dist: fw-gear<0.4,>=0.3.1
Requires-Dist: pandas<3,>=2
